cvxRiskOpt/__init__.py
cvxRiskOpt/cclp_risk_opt.py
cvxRiskOpt/mpc_helpers.py
cvxRiskOpt/wass_risk_opt_pb.py
cvxRiskOpt-0.2.0.dist-info/LICENSE
cvxRiskOpt-0.2.0.dist-info/METADATA
cvxRiskOpt-0.2.0.dist-info/WHEEL
cvxRiskOpt-0.2.0.dist-info/top_level.txt
cvxRiskOpt-0.2.0.dist-info/RECORD
