Metadata-Version: 2.1
Name: cvxRiskOpt
Version: 0.2.0
Summary: Risk-Based Optimization tool using CVXPY and CVXPYgen
Home-page: https://github.com/TSummersLab/cvxRiskOpt
Author: Sleiman Safaoui, Tyler Summers
Author-email: snsafaoui@gmail.com, tyler.summers@utdallas.edu
Maintainer: Sleiman Safaoui
Maintainer-email: snsafaoui@gmail.com
License: Apache-2.0
Keywords: dro,risk,optimization,robust,code generation,mpc
Requires-Python: >=3.10
License-File: LICENSE
Requires-Dist: scipy >=1.11.4
Requires-Dist: numpy >=1.26.2
Requires-Dist: matplotlib >=3.8.0
Requires-Dist: cvxpygen >=0.3.5
Requires-Dist: cvxpy >=1.4.3
Provides-Extra: dev
Requires-Dist: pytest ==7.4.0 ; extra == 'dev'
Requires-Dist: polytope ==0.2.5 ; extra == 'dev'
Requires-Dist: Sphinx ==7.2.6 ; extra == 'dev'
